centra_sdk/__init__.py
centra_sdk/dependencies.py
centra_sdk/main.py
centra_sdk/models/connector/__init__.py
centra_sdk/models/connector/v1/__init__.py
centra_sdk/models/connector/v1/common/__init__.py
centra_sdk/models/connector/v1/common/common.py
centra_sdk/models/connector/v1/common/inventory.py
centra_sdk/models/connector/v1/consumer/__init__.py
centra_sdk/models/connector/v1/consumer/agents.py
centra_sdk/models/connector/v1/consumer/enforcement.py
centra_sdk/models/connector/v1/k8s/__init__.py
centra_sdk/models/connector/v1/k8s/k8s_inventory.py
centra_sdk/models/connector/v1/operations/__init__.py
centra_sdk/models/connector/v1/operations/aws/__init__.py
centra_sdk/models/connector/v1/operations/aws/accounts.py
centra_sdk/models/connector/v1/operations/azure/__init__.py
centra_sdk/models/connector/v1/operations/azure/setup.py
centra_sdk/models/connector/v1/operations/config.py
centra_sdk/models/connector/v1/operations/health.py
centra_sdk/models/connector/v1/operations/info.py
centra_sdk/models/connector/v1/operations/log.py
centra_sdk/models/connector/v1/operations/onboard.py
centra_sdk/models/connector/v1/provider/__init__.py
centra_sdk/models/connector/v1/provider/inventory.py
centra_sdk/models/connector/v1/provider/lookup.py
centra_sdk/models/connector/v1/provider/reveal.py
centra_sdk/models/connector/version.py
centra_sdk/routers/account.py
centra_sdk/routers/agents.py
centra_sdk/routers/authentication.py
centra_sdk/routers/control.py
centra_sdk/routers/enforcement.py
centra_sdk/routers/health.py
centra_sdk/routers/info.py
centra_sdk/routers/inventory.py
centra_sdk/routers/logging.py
centra_sdk/routers/onboarding.py
centra_sdk/routers/operations.py
centra_sdk/routers/setup.py
centra_sdk/utils/auth.py
centra_sdk/utils/context.py
centra_sdk/utils/gc_cli.py
centra_sdk/utils/gc_handler.py
centra_sdk/utils/gc_serializer.py
centra_sdk/utils/handler_registry.py
centra_sdk/utils/log_handling.py
centra_sdk/utils/option_values_handler.py
centra_sdk-0.1.31.dist-info/METADATA
centra_sdk-0.1.31.dist-info/WHEEL
centra_sdk-0.1.31.dist-info/entry_points.txt
centra_sdk-0.1.31.dist-info/RECORD
