Metadata-Version: 2.4
Name: centra-sdk
Version: 0.1.31
Summary: 
License: MIT
Author: ivasylenko
Author-email: ivasylen@akamai.com
Requires-Python: >=3.9,<3.13
Classifier: License :: OSI Approved :: MIT License
Classifier: Programming Language :: Python :: 3
Classifier: Programming Language :: Python :: 3.9
Classifier: Programming Language :: Python :: 3.10
Classifier: Programming Language :: Python :: 3.11
Classifier: Programming Language :: Python :: 3.12
Requires-Dist: click (>=8.0.0,<8.2.0)
Requires-Dist: fastapi (>=0.120.1,<0.122)
Requires-Dist: httpx (>=0.28.1)
Requires-Dist: pyjwt (>=2.10.1,<3.0.0)
Requires-Dist: rich (>=13.0.0)
Project-URL: Homepage, https://github.com/guardicore/contracts
Project-URL: Repository, https://github.com/guardicore/contracts
